lqg/__init__.py
lqg/belief/__init__.py
lqg/belief/kf.py
lqg/ccg.py
lqg/control/__init__.py
lqg/control/lqr.py
lqg/infer/__init__.py
lqg/infer/mle.py
lqg/infer/models.py
lqg/infer/prior.py
lqg/infer/utils.py
lqg/io.py
lqg/lqg.py
lqg/optim.py
lqg/spec.py
lqg/tracking/__init__.py
lqg/tracking/basic.py
lqg/tracking/delay.py
lqg/tracking/subjective.py
lqg/utils.py
lqg-0.2.11.dist-info/LICENSE
lqg-0.2.11.dist-info/METADATA
lqg-0.2.11.dist-info/WHEEL
lqg-0.2.11.dist-info/RECORD
