Metadata-Version: 2.3
Name: lqg
Version: 0.2.11
Summary: (Inverse) optimal control for linear-quadratic Gaussian systems
License: AGPL-3.0-only
Author: Dominik Straub
Author-email: dominikstrb@mailbox.org
Requires-Python: >=3.10
Classifier: License :: OSI Approved :: GNU Affero General Public License v3
Classifier: Programming Language :: Python :: 3
Classifier: Programming Language :: Python :: 3.10
Classifier: Programming Language :: Python :: 3.11
Classifier: Programming Language :: Python :: 3.12
Classifier: Programming Language :: Python :: 3.13
Requires-Dist: arviz (>=0.16.1)
Requires-Dist: jax (>=0.4.13)
Requires-Dist: matplotlib (>=3.2.2)
Requires-Dist: numpyro (>=0.12.1)
